ezDT.py
simpleDT.py
ezDT-0.0.2.dist-info/METADATA
ezDT-0.0.2.dist-info/WHEEL
ezDT-0.0.2.dist-info/top_level.txt
ezDT-0.0.2.dist-info/RECORD
