Metadata-Version: 2.1
Name: ezDT
Version: 0.0.2
Summary: Simple datetime functions
Home-page: https://github.com/jblarson/ezDT
Author: JB Larson
License: UNKNOWN
Platform: UNKNOWN
Classifier: Programming Language :: Python :: 3
Classifier: Programming Language :: Python :: 3.6
Classifier: Programming Language :: Python :: 3.7
Classifier: License :: OSI Approved :: BSD License
Classifier: Operating System :: OS Independent
